{
  "id": "4_CCR_723-16",
  "canonical_item_id": "4_CCR_723-16",
  "entity_type": "regulation_rule_acquisition",
  "title": "4 CCR 723-16",
  "rule_name": null,
  "department": "700 Department of Regulatory Agencies",
  "department_normalized": "Department of Regulatory Agencies",
  "agency": "723 Public Utilities Commission",
  "agency_normalized": "Public Utilities Commission",
  "division_board_program": "Public Utilities Commission",
  "ccr_citation": "4 CCR 723-16",
  "department_number": "4",
  "chapter": "723",
  "rule_number": "16",
  "source_page_url": "https://www.sos.state.co.us/CCR/DisplayRule.do?action=ruleinfo&ruleId=2272&deptID=18&agencyID=96&deptName=Department%20of%20Regulatory%20Agencies&agencyName=Public%20Utilities%20Commission&seriesNum=4%20CCR%20723-16",
  "document_url": "https://www.sos.state.co.us/CCR/GenerateRulePdf.do?ruleVersionId=739&fileName=4%20CCR%20723-16&type=pdf",
  "archive_raw_file_path": "C:/Users/jpfeifer/OneDrive - CoorsTek/Documents/Geode/_RAW_ARCHIVE/ccr/4_CCR_723-16.pdf",
  "normalized_output_path": "02_Regulations_CCR/_normalized/records/4_CCR_723-16.json",
  "metadata_output_path": "02_Regulations_CCR/_meta/ccr_normalized_meta.jsonl",
  "content_type": "application/pdf",
  "source_format": "pdf",
  "discovery_timestamp": "2026-07-02T17:32:01.073040Z",
  "retrieval_timestamp": "2026-06-22T22:34:25.974139Z",
  "normalization_timestamp": "2026-07-02T17:36:26.106814Z",
  "normalization_status": "normalized",
  "status": "skipped_existing",
  "checksum_sha256": "afb4306ee0b58ba7f1d1766cac9d3d17abe74fd9450521c59099a073f6ef64ab",
  "size_bytes": 312385,
  "raw_file_exists": true,
  "text_extraction_status": "not_attempted",
  "text_output_path": null,
  "notes": null,
  "error": null
}
