{
  "id": "8_CCR_1202-13",
  "canonical_item_id": "8_CCR_1202-13",
  "entity_type": "regulation_rule_acquisition",
  "title": "8 CCR 1202-13",
  "rule_name": null,
  "department": "1200 Department of Agriculture",
  "department_normalized": "Department of Agriculture",
  "agency": "1202 Inspection and Consumer Services Division",
  "agency_normalized": "Inspection and Consumer Services Division",
  "division_board_program": "Inspection and Consumer Services Division",
  "ccr_citation": "8 CCR 1202-13",
  "department_number": "8",
  "chapter": "1202",
  "rule_number": "13",
  "source_page_url": "https://www.sos.state.co.us/CCR/DisplayRule.do?action=ruleinfo&ruleId=3054&deptID=1&agencyID=56&deptName=Department%20of%20Agriculture&agencyName=Inspection%20and%20Consumer%20Services%20Division&seriesNum=8%20CCR%201202-13",
  "document_url": "https://www.sos.state.co.us/CCR/GenerateRulePdf.do?ruleVersionId=8086&fileName=8%20CCR%201202-13&type=pdf",
  "archive_raw_file_path": "C:/Users/jpfeifer/OneDrive - CoorsTek/Documents/Geode/_RAW_ARCHIVE/ccr/8_CCR_1202-13.pdf",
  "normalized_output_path": "02_Regulations_CCR/_normalized/records/8_CCR_1202-13.json",
  "metadata_output_path": "02_Regulations_CCR/_meta/ccr_normalized_meta.jsonl",
  "content_type": "application/pdf",
  "source_format": "pdf",
  "discovery_timestamp": "2026-07-02T17:32:25.124784Z",
  "retrieval_timestamp": "2026-06-23T14:40:58.504478Z",
  "normalization_timestamp": "2026-07-02T17:36:26.106814Z",
  "normalization_status": "normalized",
  "status": "skipped_existing",
  "checksum_sha256": "48b0c5ad650bc67392105430bb4c1f60b742b284bfd1edcce2e2bd693ff3b94a",
  "size_bytes": 342391,
  "raw_file_exists": true,
  "text_extraction_status": "not_attempted",
  "text_output_path": null,
  "notes": null,
  "error": null
}
