{
  "id": "8_CCR_1206-4",
  "canonical_item_id": "8_CCR_1206-4",
  "entity_type": "regulation_rule_acquisition",
  "title": "8 CCR 1206-4",
  "rule_name": null,
  "department": "1200 Department of Agriculture",
  "department_normalized": "Department of Agriculture",
  "agency": "1206 Conservation Services Division",
  "agency_normalized": "Conservation Services Division",
  "division_board_program": "Conservation Services Division",
  "ccr_citation": "8 CCR 1206-4",
  "department_number": "8",
  "chapter": "1206",
  "rule_number": "4",
  "source_page_url": "https://www.sos.state.co.us/CCR/DisplayRule.do?action=ruleinfo&ruleId=3285&deptID=1&agencyID=163&deptName=Department%20of%20Agriculture&agencyName=Conservation%20Services%20Division&seriesNum=8%20CCR%201206-4",
  "document_url": "https://www.sos.state.co.us/CCR/GenerateRulePdf.do?ruleVersionId=7861&fileName=8%20CCR%201206-4&type=pdf",
  "archive_raw_file_path": "C:/Users/jpfeifer/OneDrive - CoorsTek/Documents/Geode/_RAW_ARCHIVE/ccr/8_CCR_1206-4.pdf",
  "normalized_output_path": "02_Regulations_CCR/_normalized/records/8_CCR_1206-4.json",
  "metadata_output_path": "02_Regulations_CCR/_meta/ccr_normalized_meta.jsonl",
  "content_type": "application/pdf",
  "source_format": "pdf",
  "discovery_timestamp": "2026-07-02T17:32:27.704691Z",
  "retrieval_timestamp": "2026-06-23T14:42:19.559946Z",
  "normalization_timestamp": "2026-07-02T17:36:26.106814Z",
  "normalization_status": "normalized",
  "status": "skipped_existing",
  "checksum_sha256": "3a3d70b687fc8e5acaa3aa1b99824c4da81c64aed0dfa5571eb7f98566ca20f8",
  "size_bytes": 336764,
  "raw_file_exists": true,
  "text_extraction_status": "not_attempted",
  "text_output_path": null,
  "notes": null,
  "error": null
}
