{
  "id": "8_CCR_1205-3",
  "canonical_item_id": "8_CCR_1205-3",
  "entity_type": "regulation_rule_acquisition",
  "title": "8 CCR 1205-3",
  "rule_name": null,
  "department": "1200 Department of Agriculture",
  "department_normalized": "Department of Agriculture",
  "agency": "1205 State Board of Stock Inspection Commissioners",
  "agency_normalized": "State Board of Stock Inspection Commissioners",
  "division_board_program": "State Board of Stock Inspection Commissioners",
  "ccr_citation": "8 CCR 1205-3",
  "department_number": "8",
  "chapter": "1205",
  "rule_number": "3",
  "source_page_url": "https://www.sos.state.co.us/CCR/DisplayRule.do?action=ruleinfo&ruleId=2560&deptID=1&agencyID=120&deptName=Department%20of%20Agriculture&agencyName=State%20Board%20of%20Stock%20Inspection%20Commissioners&seriesNum=8%20CCR%201205-3",
  "document_url": "https://www.sos.state.co.us/CCR/GenerateRulePdf.do?ruleVersionId=12130&fileName=8%20CCR%201205-3&type=pdf",
  "archive_raw_file_path": "C:/Users/jpfeifer/OneDrive - CoorsTek/Documents/Geode/_RAW_ARCHIVE/ccr/8_CCR_1205-3.pdf",
  "normalized_output_path": "02_Regulations_CCR/_normalized/records/8_CCR_1205-3.json",
  "metadata_output_path": "02_Regulations_CCR/_meta/ccr_normalized_meta.jsonl",
  "content_type": "application/pdf",
  "source_format": "pdf",
  "discovery_timestamp": "2026-07-02T17:32:27.076327Z",
  "retrieval_timestamp": "2026-06-23T14:42:06.777583Z",
  "normalization_timestamp": "2026-07-02T17:36:26.106814Z",
  "normalization_status": "normalized",
  "status": "skipped_existing",
  "checksum_sha256": "fba49e703b2d96d8ee0dc7ec001e271877cf1c1982682bf1daf680197d998286",
  "size_bytes": 399661,
  "raw_file_exists": true,
  "text_extraction_status": "not_attempted",
  "text_output_path": null,
  "notes": null,
  "error": null
}
