{
  "behaviorEvents": [
    {
      "eventId": "f40f6407-2def-4f4b-9b57-0216386f4294",
      "payload": {
        "pathname": "/app/dashboard"
      },
      "recordedAt": "2026-06-30T19:32:13.064Z",
      "source": "behavior",
      "type": "route_view"
    }
  ],
  "explicitAnswers": [
    {
      "answeredAt": "2026-06-30T19:32:13.062Z",
      "key": "displayName",
      "sensitivity": "public",
      "source": "explicit",
      "value": "JP"
    }
  ],
  "schemaVersion": 1,
  "updatedAt": "2026-06-30T19:32:13.064Z",
  "userId": "anon-10fb3bab-a2f0-4378-864f-5a5fcf2ae042",
  "derived": {
    "agencyVector": [],
    "behaviorScore": 11,
    "confidence": 0.17,
    "displayName": "JP",
    "initials": "J",
    "industryVector": [],
    "lastActiveAt": "2026-06-30T19:32:13.064Z",
    "modelVersion": 2,
    "preferredTone": "direct",
    "primaryInterest": "dashboard",
    "readingDensity": "light",
    "recomputedAt": "2026-06-30T19:32:13.064Z",
    "roleVector": [
      {
        "key": "executive",
        "weight": 1
      }
    ],
    "surfaceVector": [
      {
        "key": "dashboard",
        "weight": 1
      }
    ],
    "topicSignals": [
      {
        "key": "dashboard",
        "weight": 1
      }
    ]
  }
}
