{
  "behaviorEvents": [],
  "explicitAnswers": [
    {
      "answeredAt": "2026-06-29T15:22:37.038Z",
      "key": "displayName",
      "sensitivity": "public",
      "source": "explicit",
      "value": "JP"
    }
  ],
  "schemaVersion": 1,
  "updatedAt": "2026-06-29T15:22:37.038Z",
  "userId": "anon-95f53b49-3e5b-4d0e-b0e6-278dae4f0bd1",
  "derived": {
    "agencyVector": [],
    "behaviorScore": 0,
    "confidence": 0.15,
    "displayName": "JP",
    "initials": "J",
    "industryVector": [],
    "lastActiveAt": "2026-06-29T15:22:37.038Z",
    "modelVersion": 2,
    "preferredTone": "direct",
    "primaryInterest": null,
    "readingDensity": "light",
    "recomputedAt": "2026-06-29T15:22:37.038Z",
    "roleVector": [],
    "surfaceVector": [],
    "topicSignals": []
  }
}
