{
  "behaviorEvents": [],
  "explicitAnswers": [
    {
      "answeredAt": "2026-07-01T20:26:11.794Z",
      "key": "displayName",
      "sensitivity": "public",
      "source": "explicit",
      "value": "JP"
    }
  ],
  "schemaVersion": 1,
  "updatedAt": "2026-07-01T20:26:11.794Z",
  "userId": "anon-acb8c258-1e5d-447f-89d9-ec30d7c1555c",
  "derived": {
    "agencyVector": [],
    "behaviorScore": 0,
    "confidence": 0.15,
    "displayName": "JP",
    "initials": "J",
    "industryVector": [],
    "lastActiveAt": "2026-07-01T20:26:11.794Z",
    "modelVersion": 2,
    "preferredTone": "direct",
    "primaryInterest": null,
    "readingDensity": "light",
    "recomputedAt": "2026-07-01T20:26:11.794Z",
    "roleVector": [],
    "surfaceVector": [],
    "topicSignals": []
  }
}
