{
  "behaviorEvents": [],
  "explicitAnswers": [
    {
      "answeredAt": "2026-06-26T20:11:41.427Z",
      "key": "displayName",
      "sensitivity": "public",
      "source": "explicit",
      "value": "JP"
    }
  ],
  "schemaVersion": 1,
  "updatedAt": "2026-06-26T20:11:41.427Z",
  "userId": "anon-bffe9697-7ebc-4d9d-a3c7-904150f3fc25",
  "derived": {
    "agencyVector": [],
    "behaviorScore": 0,
    "confidence": 0.15,
    "displayName": "JP",
    "initials": "J",
    "industryVector": [],
    "lastActiveAt": "2026-06-26T20:11:41.427Z",
    "modelVersion": 2,
    "preferredTone": "direct",
    "primaryInterest": null,
    "readingDensity": "light",
    "recomputedAt": "2026-06-26T20:11:41.427Z",
    "roleVector": [],
    "surfaceVector": [],
    "topicSignals": []
  }
}
