{
  "behaviorEvents": [],
  "explicitAnswers": [
    {
      "answeredAt": "2026-06-25T22:20:18.372Z",
      "key": "displayName",
      "sensitivity": "public",
      "source": "explicit",
      "value": "JP"
    }
  ],
  "schemaVersion": 1,
  "updatedAt": "2026-06-25T22:20:18.372Z",
  "userId": "anon-05e8d623-fac5-4843-8479-7df308c5f246",
  "derived": {
    "agencyVector": [],
    "behaviorScore": 0,
    "confidence": 0.15,
    "displayName": "JP",
    "initials": "J",
    "industryVector": [],
    "lastActiveAt": "2026-06-25T22:20:18.372Z",
    "modelVersion": 2,
    "preferredTone": "direct",
    "primaryInterest": null,
    "readingDensity": "light",
    "recomputedAt": "2026-06-25T22:20:18.372Z",
    "roleVector": [],
    "surfaceVector": [],
    "topicSignals": []
  }
}
