{
  "behaviorEvents": [],
  "explicitAnswers": [
    {
      "answeredAt": "2026-06-25T21:08:25.436Z",
      "key": "displayName",
      "sensitivity": "public",
      "source": "explicit",
      "value": "JP"
    }
  ],
  "schemaVersion": 1,
  "updatedAt": "2026-06-25T21:08:25.436Z",
  "userId": "anon-37fed5a2-8e62-42dc-941c-d74baf4ec9f5",
  "derived": {
    "behaviorScore": 0,
    "displayName": "JP",
    "initials": "J",
    "lastActiveAt": "2026-06-25T21:08:25.436Z",
    "primaryInterest": null,
    "preferredTone": "direct",
    "topicSignals": []
  }
}
