{
  "behaviorEvents": [],
  "explicitAnswers": [
    {
      "answeredAt": "2026-07-01T22:22:51.926Z",
      "key": "displayName",
      "sensitivity": "public",
      "source": "explicit",
      "value": "JP"
    }
  ],
  "schemaVersion": 1,
  "updatedAt": "2026-07-01T22:22:51.926Z",
  "userId": "anon-34bc3ec2-125a-4a1f-9ac0-4bb5d16352fa",
  "derived": {
    "agencyVector": [],
    "behaviorScore": 0,
    "confidence": 0.15,
    "displayName": "JP",
    "initials": "J",
    "industryVector": [],
    "lastActiveAt": "2026-07-01T22:22:51.926Z",
    "modelVersion": 2,
    "preferredTone": "direct",
    "primaryInterest": null,
    "readingDensity": "light",
    "recomputedAt": "2026-07-01T22:22:51.926Z",
    "roleVector": [],
    "surfaceVector": [],
    "topicSignals": []
  }
}
