{
  "behaviorEvents": [],
  "explicitAnswers": [
    {
      "answeredAt": "2026-06-26T21:38:05.027Z",
      "key": "displayName",
      "sensitivity": "public",
      "source": "explicit",
      "value": "JP"
    }
  ],
  "schemaVersion": 1,
  "updatedAt": "2026-06-26T21:38:05.027Z",
  "userId": "anon-dd33c26d-fb9d-4c1c-ba1a-6c89913771da",
  "derived": {
    "agencyVector": [],
    "behaviorScore": 0,
    "confidence": 0.15,
    "displayName": "JP",
    "initials": "J",
    "industryVector": [],
    "lastActiveAt": "2026-06-26T21:38:05.027Z",
    "modelVersion": 2,
    "preferredTone": "direct",
    "primaryInterest": null,
    "readingDensity": "light",
    "recomputedAt": "2026-06-26T21:38:05.027Z",
    "roleVector": [],
    "surfaceVector": [],
    "topicSignals": []
  }
}
