{
  "behaviorEvents": [
    {
      "eventId": "3080dab5-8f22-439e-bdf2-b7390ba68e87",
      "payload": {
        "pathname": "/"
      },
      "recordedAt": "2026-06-29T16:49:00.013Z",
      "source": "behavior",
      "type": "route_view"
    }
  ],
  "explicitAnswers": [
    {
      "answeredAt": "2026-06-29T16:49:00.011Z",
      "key": "displayName",
      "sensitivity": "public",
      "source": "explicit",
      "value": "JP"
    }
  ],
  "schemaVersion": 1,
  "updatedAt": "2026-06-29T16:49:00.013Z",
  "userId": "anon-54045f80-311f-4ccd-b553-27243eccbfcf",
  "derived": {
    "agencyVector": [],
    "behaviorScore": 11,
    "confidence": 0.17,
    "displayName": "JP",
    "initials": "J",
    "industryVector": [],
    "lastActiveAt": "2026-06-29T16:49:00.013Z",
    "modelVersion": 2,
    "preferredTone": "direct",
    "primaryInterest": "dashboard",
    "readingDensity": "light",
    "recomputedAt": "2026-06-29T16:49:00.014Z",
    "roleVector": [],
    "surfaceVector": [
      {
        "key": "dashboard",
        "weight": 1
      }
    ],
    "topicSignals": [
      {
        "key": "dashboard",
        "weight": 1
      }
    ]
  }
}
